{
  "cache_time": 7200,
  "api_site": {
    "fq8s": {
      "name": "茅台资源站采集接口",
      "api": "https://caiji.maotaizy.cc/api.php/provide/vod"
    },
    "z0ur": {
      "name": "如意资源网采集接口",
      "api": "https://cj.rycjapi.com/api.php/provide/vod"
    },
    "shhx": {
      "name": "影剧资源网采集接口",
      "api": "https://caiji.maotaizy.cc/api.php/provide/vod"
    },
    "rqji": {
      "name": "黑料资源网采集接口大全",
      "api": "https://www.heiliaozyapi.com/api.php/provide/vod"
    },
    "i213": {
      "name": "香蕉资源网采集接口",
      "api": "https://www.xiangjiaozyw.com/api.php/provide/vod"
    },
    "ff6o": {
      "name": "红牛云播资源采集地址",
      "api": "https://www.hongniuzy2.com/api.php/provide/vod"
    },
    "ybjl": {
      "name": "光速资源站采集接口地址",
      "api": "https://api.guangsuapi.com/api.php/provide/vod"
    },
    "jx7h": {
      "name": "速播资源采集规则地址",
      "api": "https://subocj.com/api.php/provide/vod"
    },
    "94pa": {
      "name": "豪华资源网采集接口地址",
      "api": "https://hhzyapi.com/api.php/provide/vod"
    },
    "gksv": {
      "name": "虎牙资源采集网采集接口",
      "api": "https://www.huyaapi.com/api.php/provide/vod"
    },
    "bf7h": {
      "name": "91精品资源网采集接口",
      "api": "https://91jpzyw.com/api.php/provide/vod"
    },
    "7y4v": {
      "name": "幸资源站采集接口",
      "api": "https://xzybb1.com/api.php/provide/vod"
    },
    "xpa4": {
      "name": "爱奇艺资源站采集接口",
      "api": "https://www.iqiyizyapi.com/api.php/provide/vod"
    },
    "9put": {
      "name": "奶香香资源站采集接口",
      "api": "https://Naixxzy.com/api.php/provide/vod"
    },
    "ivzp": {
      "name": "魔都动漫资源采集网采集接口",
      "api": "https://www.mdzyapi.com/api.php/provide/vod"
    },
    "yjmr": {
      "name": "奥斯卡资源API采集接口大全",
      "api": "https://aosikazy.com/api.php/provide/vod"
    },
    "frqk": {
      "name": "玉兔资源采集接口",
      "api": "https://apiyutu.com/api.php/provide/vod"
    },
    "aqp9": {
      "name": "ikun资源网采集接口",
      "api": "https://ikunzyapi.com/api.php/provide/vod"
    },
    "q3hf": {
      "name": "789官采资源站采集接口",
      "api": "https://www.caiji.cyou/api.php/provide/vod"
    },
    "orci": {
      "name": "猫眼资源站采集接口",
      "api": "https://api.maoyanapi.top/api.php/provide/vod"
    },
    "na9o": {
      "name": "旺旺资源网采集接口",
      "api": "https://api.wwzy.tv/api.php/provide/vod"
    },
    "cx12": {
      "name": "155资源站采集接口",
      "api": "https://155api.com/api.php/provide/vod"
    },
    "a90z": {
      "name": "搜av资源站采集接口",
      "api": "https://api.souavzy.vip/api.php/provide/vod"
    },
    "8wry": {
      "name": "OK资源采集网采集接口",
      "api": "http://api.okzyw.net/api.php/provide/vod"
    },
    "qn5i": {
      "name": "金蝉官采影视采集站采集接口",
      "api": "http://zy.jinchancaiji.com/api.php/provide/vod"
    },
    "eb6o": {
      "name": "豆豆资源网采集接口",
      "api": "https://api.douapi.cc/api.php/provide/vod"
    },
    "kb5e": {
      "name": "山海官方资源站采集接口",
      "api": "https://zy.sh0o.cn/api.php/provide/vod"
    },
    "m7dz": {
      "name": "U酷资源网采集地址",
      "api": "https://api.ukuapi88.com/api.php/provide/vod"
    },
    "n7oq": {
      "name": "量子资源网资源采集接口",
      "api": "https://cj.lziapi.com/api.php/provide/vod"
    },
    "8twf": {
      "name": "快车资源采集站采集接口",
      "api": "https://caiji.kczyapi.com/api.php/provide/vod"
    },
    "17x8": {
      "name": "最大资源网采集接口",
      "api": "https://api.zuidapi.com/api.php/provide/vod"
    },
    "yuqw": {
      "name": "大奶子资源网采集接口",
      "api": "https://apidanaizi.com/api.php/provide/vod"
    },
    "rkki": {
      "name": "天涯影视资源网采集接口",
      "api": "https://tyyszyapi.com/api.php/provide/vod"
    },
    "7s9h": {
      "name": "电影天堂采集综合资源接口",
      "api": "http://caiji.dyttzyapi.com/api.php/provide/vod"
    },
    "wjjz": {
      "name": "百度资源采集接口",
      "api": "https://api.apibdzy.com/api.php/provide/vod"
    },
    "xjnh": {
      "name": "X细胞资源网采集接口",
      "api": "https://www.xxibaozyw.com/api.php/provide/vod"
    },
    "lv4t": {
      "name": "火花官采收费影视资源站采集接口",
      "api": "http://cj.huohua.vip/api.php/provide/vod"
    },
    "fmhc": {
      "name": "百万资源网采集接口",
      "api": "https://api.bwzyz.com/api.php/provide/vod"
    },
    "huy0": {
      "name": "老色逼资源站采集接口",
      "api": "https://apilsbzy1.com/api.php/provide/vod"
    },
    "adt5": {
      "name": "鸭鸭（丫丫）资源网采集接口",
      "api": "https://cj.yayazy.net/api.php/provide/vod"
    },
    "079n": {
      "name": "牛牛资源网采集接口",
      "api": "https://api.niuniuzy.me/api.php/provide/vod"
    },
    "jei4": {
      "name": "360资源站采集接口",
      "api": "https://360zyzz.com/api.php/provide/vod"
    },
    "vabx": {
      "name": "爱坤联盟资源网采集接口",
      "api": "https://www.jkunzyapi.com/api.php/provide/vod"
    },
    "gl76": {
      "name": "卧龙影视资源采集站采集接口",
      "api": "https://collect.wolongzy.cc/api.php/provide/vod"
    },
    "mmj1": {
      "name": "极速资源网采集接口",
      "api": "https://jszyapi.com/api.php/provide/vod"
    },
    "l24z": {
      "name": "暴风资源网采集接口",
      "api": "https://bfzyapi.com/api.php/provide/vod"
    },
    "dnqd": {
      "name": "大地资源采集接口",
      "api": "https://dadiapi.com/api.php/provide/vod"
    },
    "jd6b": {
      "name": "非凡资源网采集接口",
      "api": "http://api.ffzyapi.com/api.php/provide/vod"
    },
    "6qq9": {
      "name": "CK资源采集接口",
      "api": "https://ckzy.me/api.php/provide/vod"
    },
    "pm3t": {
      "name": "森林资源网采集接口",
      "api": "https://slapibf.com/api.php/provide/vod"
    },
    "zwoz": {
      "name": "辣椒资源网采集接口",
      "api": "https://apilj.com/api.php/provide/vod"
    },
    "b8no": {
      "name": "麒麟资源站全站采集接口",
      "api": "http://www.qilinzyz.com/api.php/provide/vod"
    },
    "gm9t": {
      "name": "樱花资源网采集接口",
      "api": "https://m3u8.apiyhzy.com/api.php/provide/vod"
    },
    "970i": {
      "name": "无尽资源网采集接口",
      "api": "https://api.wujinapi.me/api.php/provide/vod"
    }
  }
}